README.md
setup.py
cf_loggers/__init__.py
cf_loggers/setup.py
cf_loggers.egg-info/PKG-INFO
cf_loggers.egg-info/SOURCES.txt
cf_loggers.egg-info/dependency_links.txt
cf_loggers.egg-info/requires.txt
cf_loggers.egg-info/top_level.txt
cf_loggers/elasticsearch/__init__.py
cf_loggers/elasticsearch/handler.py
cf_loggers/elasticsearch/serializers.py